ancora/__init__.py
ancora-0.1.0.dist-info/WHEEL
ancora-0.1.0.dist-info/METADATA
ancora-0.1.0.dist-info/RECORD
