Metadata-Version: 2.1
Name: ancora
Version: 0.1.0
Summary: Stellar Anchor implementation using FastAPI
Home-page: https://github.com/talvezutil/ancora
License: Apache License Version 2.0
Author: Yuri Escalianti
Author-email: yuriescl@gmail.com
Requires-Python: >=3.11,<4.0
Classifier: License :: Other/Proprietary License
Classifier: Programming Language :: Python :: 3
Classifier: Programming Language :: Python :: 3.11
